{"_note": "Compact view (top 70 by importance, 20 methods/class). Read source_file paths for full code.", "classes": [{"name": "AuthService", "kind": "class", "source_file": "data/acc878f9-aeca-493c-bc04-48fb2d22d115/src/backend/src/services/auth/AuthService.js", "methods": [{"name": "_init", "visibility": "public"}, {"name": "authenticate_from_token", "parameters": ["token"], "visibility": "public"}, {"name": "get_user_app_token", "parameters": ["app_uid"], "visibility": "public"}, {"name": "get_site_app_token", "visibility": "public"}, {"name": "resolvePositiveInteger", "parameters": ["value", "fallback"], "visibility": "public"}, {"name": "getPrivateAssetTokenTtlSeconds", "visibility": "public"}, {"name": "getPrivateAssetCookieName", "visibility": "public"}, {"name": "getPublicHostedActorTokenTtlSeconds", "visibility": "public"}, {"name": "getPublicHostedActorCookieName", "visibility": "public"}, {"name": "normalizeHostnameForCookieDomain", "parameters": ["hostnameValue"], "visibility": "public"}, {"name": "isCookieDomainHostEligible", "parameters": ["hostnameValue"], "visibility": "public"}, {"name": "getConfiguredPrivateCookieDomains", "visibility": "public"}, {"name": "getConfiguredHostedCookieDomains", "visibility": "public"}, {"name": "resolvePrivateAssetCookieDomain", "visibility": "public"}, {"name": "getPrivateAssetCookieOptions", "visibility": "public"}, {"name": "resolvePublicHostedActorCookieDomain", "visibility": "public"}, {"name": "getPublicHostedActorCookieOptions", "visibility": "public"}, {"name": "normalizePrivateAssetSubdomain", "parameters": ["subdomain"], "visibility": "public"}, {"name": "normalizePrivateAssetHost", "parameters": ["privateHost"], "visibility": "public"}, {"name": "createPrivateAssetToken", "visibility": "public"}]}, {"name": "UI", "kind": "class", "source_file": "data/acc878f9-aeca-493c-bc04-48fb2d22d115/src/puter-js/src/modules/UI.js", "methods": [{"name": "", "parameters": ["name", "resolve"], "visibility": "public"}, {"name": "", "parameters": ["name"], "visibility": "public"}, {"name": "", "parameters": ["name", "value"], "visibility": "public"}, {"name": "", "visibility": "public"}, {"name": "constructor", "parameters": ["puter"], "visibility": "public"}, {"name": "onWindowClose", "parameters": ["callback"], "visibility": "public"}, {"name": "onItemsOpened", "parameters": ["callback"], "visibility": "public"}, {"name": "wasLaunchedWithItems", "visibility": "public"}, {"name": "onLaunchedWithItems", "parameters": ["callback"], "visibility": "public"}, {"name": "requestEmailConfirmation", "visibility": "public"}, {"name": "alert", "parameters": ["message", "buttons", "options", "callback"], "visibility": "public"}, {"name": "openDevPaymentsAccount", "visibility": "public"}, {"name": "instancesOpen", "parameters": ["callback"], "visibility": "public"}, {"name": "socialShare", "parameters": ["url", "message", "options", "callback"], "visibility": "public"}, {"name": "prompt", "parameters": ["message", "placeholder", "options", "callback"], "visibility": "public"}, {"name": "notify", "parameters": ["options"], "visibility": "public"}, {"name": "showDirectoryPicker", "parameters": ["options", "callback"], "visibility": "public"}, {"name": "showOpenFilePicker", "parameters": ["options", "callback"], "visibility": "public"}, {"name": "showFontPicker", "parameters": ["options"], "visibility": "public"}, {"name": "showColorPicker", "parameters": ["options"], "visibility": "public"}]}, {"name": "bt", "kind": "class", "source_file": "data/acc878f9-aeca-493c-bc04-48fb2d22d115/src/gui/src/lib/socket.io/socket.io.esm.min.js", "methods": [{"name": "constructor", "parameters": ["t", "e", "s"], "visibility": "public"}, {"name": "disconnected", "visibility": "public"}, {"name": "subEvents", "visibility": "public"}, {"name": "active", "visibility": "public"}, {"name": "connect", "visibility": "public"}, {"name": "open", "visibility": "public"}, {"name": "send", "visibility": "public"}, {"name": "emit", "parameters": ["t"], "visibility": "public"}, {"name": "_registerAckCallback", "parameters": ["t", "e"], "visibility": "public"}, {"name": "emitWithAck", "parameters": ["t"], "visibility": "public"}, {"name": "_addToQueue", "parameters": ["t"], "visibility": "public"}, {"name": "_drainQueue", "visibility": "public"}, {"name": "packet", "parameters": ["t"], "visibility": "public"}, {"name": "onopen", "visibility": "public"}, {"name": "_sendConnectPacket", "parameters": ["t"], "visibility": "public"}, {"name": "onerror", "parameters": ["t"], "visibility": "public"}, {"name": "onclose", "parameters": ["t", "e"], "visibility": "public"}, {"name": "onpacket", "parameters": ["t"], "visibility": "public"}, {"name": "onevent", "parameters": ["t"], "visibility": "public"}, {"name": "emitEvent", "parameters": ["t"], "visibility": "public"}]}, {"name": "AppService", "kind": "class", "source_file": "data/acc878f9-aeca-493c-bc04-48fb2d22d115/src/backend/src/modules/data-access/AppService.js", "methods": [{"name": "_init", "visibility": "public"}, {"name": "", "visibility": "public"}, {"name": "", "visibility": "public"}, {"name": "", "parameters": ["filetypes"], "visibility": "public"}, {"name": "", "parameters": ["appId"], "visibility": "public"}, {"name": "", "parameters": ["filetypesAsJSON"], "visibility": "public"}, {"name": "", "parameters": ["appIds"], "visibility": "public"}, {"name": "", "visibility": "public"}, {"name": "", "parameters": ["object", "uid", "owner_user_id", "app_owner_id"], "visibility": "public"}, {"name": "", "visibility": "public"}, {"name": "", "parameters": ["old_app", "actor"], "visibility": "public"}, {"name": "", "visibility": "public"}, {"name": "", "parameters": ["app"], "visibility": "public"}, {"name": "", "parameters": ["old_app"], "visibility": "public"}, {"name": "getAppRootDirId", "parameters": ["app"], "visibility": "public"}, {"name": "", "parameters": ["index_url", "user"], "visibility": "public"}, {"name": "", "parameters": ["domainValue"], "visibility": "public"}, {"name": "", "visibility": "public"}, {"name": "", "parameters": ["indexUrl"], "visibility": "public"}, {"name": "", "parameters": ["indexUrl"], "visibility": "public"}]}, {"name": "AppService", "kind": "class", "source_file": "data/acc878f9-aeca-493c-bc04-48fb2d22d115/src/backend/src/modules/data-access/AppService.js", "methods": [{"name": "_init", "visibility": "public"}, {"name": "", "visibility": "public"}, {"name": "", "visibility": "public"}, {"name": "", "parameters": ["filetypes"], "visibility": "public"}, {"name": "", "parameters": ["appId"], "visibility": "public"}, {"name": "", "parameters": ["filetypesAsJSON"], "visibility": "public"}, {"name": "", "parameters": ["appIds"], "visibility": "public"}, {"name": "", "visibility": "public"}, {"name": "", "parameters": ["object", "uid", "owner_user_id", "app_owner_id"], "visibility": "public"}, {"name": "", "visibility": "public"}, {"name": "", "parameters": ["old_app", "actor"], "visibility": "public"}, {"name": "", "visibility": "public"}, {"name": "", "parameters": ["app"], "visibility": "public"}, {"name": "", "parameters": ["old_app"], "visibility": "public"}, {"name": "getAppRootDirId", "parameters": ["app"], "visibility": "public"}, {"name": "", "parameters": ["index_url", "user"], "visibility": "public"}, {"name": "", "parameters": ["domainValue"], "visibility": "public"}, {"name": "", "visibility": "public"}, {"name": "", "parameters": ["indexUrl"], "visibility": "public"}, {"name": "", "parameters": ["indexUrl"], "visibility": "public"}]}, {"name": "bt", "kind": "class", "source_file": "data/acc878f9-aeca-493c-bc04-48fb2d22d115/src/puter-js/src/lib/socket.io/socket.io.esm.min.js", "methods": [{"name": "constructor", "parameters": ["t", "e", "s"], "visibility": "public"}, {"name": "disconnected", "visibility": "public"}, {"name": "subEvents", "visibility": "public"}, {"name": "active", "visibility": "public"}, {"name": "connect", "visibility": "public"}, {"name": "open", "visibility": "public"}, {"name": "send", "visibility": "public"}, {"name": "emit", "parameters": ["t"], "visibility": "public"}, {"name": "_registerAckCallback", "parameters": ["t", "e"], "visibility": "public"}, {"name": "emitWithAck", "parameters": ["t"], "visibility": "public"}, {"name": "_addToQueue", "parameters": ["t"], "visibility": "public"}, {"name": "_drainQueue", "visibility": "public"}, {"name": "packet", "parameters": ["t"], "visibility": "public"}, {"name": "onopen", "visibility": "public"}, {"name": "_sendConnectPacket", "parameters": ["t"], "visibility": "public"}, {"name": "onerror", "parameters": ["t"], "visibility": "public"}, {"name": "onclose", "parameters": ["t", "e"], "visibility": "public"}, {"name": "onpacket", "parameters": ["t"], "visibility": "public"}, {"name": "onevent", "parameters": ["t"], "visibility": "public"}, {"name": "emitEvent", "parameters": ["t"], "visibility": "public"}]}, {"name": "AppIconService", "kind": "class", "source_file": "data/acc878f9-aeca-493c-bc04-48fb2d22d115/src/backend/src/modules/apps/AppIconService.js", "methods": [{"name": "", "parameters": ["_"], "visibility": "public"}, {"name": "getSizes", "visibility": "public"}, {"name": "iconifyApps", "visibility": "public"}, {"name": "getAppIconPath", "visibility": "public"}, {"name": "getAppIconEndpointUrl", "visibility": "public"}, {"name": "normalizeAppUid", "parameters": ["appUid"], "visibility": "public"}, {"name": "isDataUrl", "parameters": ["value"], "visibility": "public"}, {"name": "isRawBase64ImageString", "parameters": ["value"], "visibility": "public"}, {"name": "normalizeRawBase64ImageString", "parameters": ["value"], "visibility": "public"}, {"name": "parseAppIconEndpointUrl", "parameters": ["iconUrl"], "visibility": "public"}, {"name": "isAppIconEndpointUrl", "parameters": ["iconUrl"], "visibility": "public"}, {"name": "isSameAppIconEndpointUrl", "visibility": "public"}, {"name": "extractPuterSubdomainFromUrl", "parameters": ["url"], "visibility": "public"}, {"name": "isPuterSubdomainUrl", "parameters": ["url"], "visibility": "public"}, {"name": "getAppIconsBaseUrl", "visibility": "public"}, {"name": "getSizedIconUrl", "visibility": "public"}, {"name": "getOriginalIconUrl", "visibility": "public"}, {"name": "ensureAppIconsDirectory", "visibility": "public"}, {"name": "getOriginalIconLookup", "visibility": "public"}, {"name": "ensureAppIconsSubdomain", "visibility": "public"}]}, {"name": "AppIconService", "kind": "class", "source_file": "data/acc878f9-aeca-493c-bc04-48fb2d22d115/src/backend/src/modules/apps/AppIconService.js", "methods": [{"name": "", "parameters": ["_"], "visibility": "public"}, {"name": "getSizes", "visibility": "public"}, {"name": "iconifyApps", "visibility": "public"}, {"name": "getAppIconPath", "visibility": "public"}, {"name": "getAppIconEndpointUrl", "visibility": "public"}, {"name": "normalizeAppUid", "parameters": ["appUid"], "visibility": "public"}, {"name": "isDataUrl", "parameters": ["value"], "visibility": "public"}, {"name": "isRawBase64ImageString", "parameters": ["value"], "visibility": "public"}, {"name": "normalizeRawBase64ImageString", "parameters": ["value"], "visibility": "public"}, {"name": "parseAppIconEndpointUrl", "parameters": ["iconUrl"], "visibility": "public"}, {"name": "isAppIconEndpointUrl", "parameters": ["iconUrl"], "visibility": "public"}, {"name": "isSameAppIconEndpointUrl", "visibility": "public"}, {"name": "extractPuterSubdomainFromUrl", "parameters": ["url"], "visibility": "public"}, {"name": "isPuterSubdomainUrl", "parameters": ["url"], "visibility": "public"}, {"name": "getAppIconsBaseUrl", "visibility": "public"}, {"name": "getSizedIconUrl", "visibility": "public"}, {"name": "getOriginalIconUrl", "visibility": "public"}, {"name": "ensureAppIconsDirectory", "visibility": "public"}, {"name": "getOriginalIconLookup", "visibility": "public"}, {"name": "ensureAppIconsSubdomain", "visibility": "public"}]}, {"name": "Perms", "kind": "class", "source_file": "data/acc878f9-aeca-493c-bc04-48fb2d22d115/src/puter-js/src/modules/Perms.js", "methods": [{"name": "constructor", "parameters": ["puter"], "visibility": "public"}, {"name": "setAuthToken", "parameters": ["authToken"], "visibility": "public"}, {"name": "setAPIOrigin", "parameters": ["APIOrigin"], "visibility": "public"}, {"name": "req_", "parameters": ["route", "body"], "visibility": "public"}, {"name": "grantUser", "parameters": ["target_username", "permission"], "visibility": "public"}, {"name": "grantGroup", "parameters": ["group_uid", "permission"], "visibility": "public"}, {"name": "grantApp", "parameters": ["app_uid", "permission"], "visibility": "public"}, {"name": "grantAppAnyUser", "parameters": ["app_uid", "permission"], "visibility": "public"}, {"name": "grantOrigin", "parameters": ["origin", "permission"], "visibility": "public"}, {"name": "revokeUser", "parameters": ["target_username", "permission"], "visibility": "public"}, {"name": "revokeGroup", "parameters": ["group_uid", "permission"], "visibility": "public"}, {"name": "revokeApp", "parameters": ["app_uid", "permission"], "visibility": "public"}, {"name": "revokeAppAnyUser", "parameters": ["app_uid", "permission"], "visibility": "public"}, {"name": "revokeOrigin", "parameters": ["origin", "permission"], "visibility": "public"}, {"name": "createGroup", "visibility": "public"}, {"name": "addUsersToGroup", "parameters": ["uid", "usernames"], "visibility": "public"}, {"name": "removeUsersFromGroup", "parameters": ["uid", "usernames"], "visibility": "public"}, {"name": "listGroups", "visibility": "public"}, {"name": "requestPermission", "visibility": "public"}, {"name": "request", "parameters": ["permission"], "visibility": "public"}]}, {"name": "Perms", "kind": "class", "source_file": "data/acc878f9-aeca-493c-bc04-48fb2d22d115/src/puter-js/src/modules/Perms.js", "methods": [{"name": "constructor", "parameters": ["puter"], "visibility": "public"}, {"name": "setAuthToken", "parameters": ["authToken"], "visibility": "public"}, {"name": "setAPIOrigin", "parameters": ["APIOrigin"], "visibility": "public"}, {"name": "req_", "parameters": ["route", "body"], "visibility": "public"}, {"name": "grantUser", "parameters": ["target_username", "permission"], "visibility": "public"}, {"name": "grantGroup", "parameters": ["group_uid", "permission"], "visibility": "public"}, {"name": "grantApp", "parameters": ["app_uid", "permission"], "visibility": "public"}, {"name": "grantAppAnyUser", "parameters": ["app_uid", "permission"], "visibility": "public"}, {"name": "grantOrigin", "parameters": ["origin", "permission"], "visibility": "public"}, {"name": "revokeUser", "parameters": ["target_username", "permission"], "visibility": "public"}, {"name": "revokeGroup", "parameters": ["group_uid", "permission"], "visibility": "public"}, {"name": "revokeApp", "parameters": ["app_uid", "permission"], "visibility": "public"}, {"name": "revokeAppAnyUser", "parameters": ["app_uid", "permission"], "visibility": "public"}, {"name": "revokeOrigin", "parameters": ["origin", "permission"], "visibility": "public"}, {"name": "createGroup", "visibility": "public"}, {"name": "addUsersToGroup", "parameters": ["uid", "usernames"], "visibility": "public"}, {"name": "removeUsersFromGroup", "parameters": ["uid", "usernames"], "visibility": "public"}, {"name": "listGroups", "visibility": "public"}, {"name": "requestPermission", "visibility": "public"}, {"name": "request", "parameters": ["permission"], "visibility": "public"}]}, {"name": "FSNodeContext", "kind": "class", "source_file": "data/acc878f9-aeca-493c-bc04-48fb2d22d115/src/backend/src/deprecated/filesystem/FSNodeContext.js", "methods": [{"name": "constructor", "visibility": "public"}, {"name": "selector", "parameters": ["new_selector"], "visibility": "public"}, {"name": "selector", "visibility": "public"}, {"name": "get_selector_of_type", "parameters": ["cls"], "visibility": "public"}, {"name": "get_optimal_selector", "visibility": "public"}, {"name": "isRoot", "visibility": "public"}, {"name": "isUserDirectory", "visibility": "public"}, {"name": "isAppDataDirectory", "visibility": "public"}, {"name": "isPublic", "visibility": "public"}, {"name": "getPathComponents", "visibility": "public"}, {"name": "getUserPart", "visibility": "public"}, {"name": "getPathSize", "visibility": "public"}, {"name": "exists", "visibility": "public"}, {"name": "fetchPath", "visibility": "public"}, {"name": "", "parameters": ["uuid"], "visibility": "public"}, {"name": "fetchEntry", "visibility": "public"}, {"name": "awaitStableEntry", "visibility": "public"}, {"name": "fetchSubdomains", "parameters": ["user", "_force"], "visibility": "public"}, {"name": "applySingleSubdomain", "parameters": ["sd"], "visibility": "public"}, {"name": "fetchOwner", "parameters": ["_force"], "visibility": "public"}]}, {"name": "FSNodeContext", "kind": "class", "source_file": "data/acc878f9-aeca-493c-bc04-48fb2d22d115/src/backend/src/deprecated/filesystem/FSNodeContext.js", "methods": [{"name": "constructor", "visibility": "public"}, {"name": "selector", "parameters": ["new_selector"], "visibility": "public"}, {"name": "selector", "visibility": "public"}, {"name": "get_selector_of_type", "parameters": ["cls"], "visibility": "public"}, {"name": "get_optimal_selector", "visibility": "public"}, {"name": "isRoot", "visibility": "public"}, {"name": "isUserDirectory", "visibility": "public"}, {"name": "isAppDataDirectory", "visibility": "public"}, {"name": "isPublic", "visibility": "public"}, {"name": "getPathComponents", "visibility": "public"}, {"name": "getUserPart", "visibility": "public"}, {"name": "getPathSize", "visibility": "public"}, {"name": "exists", "visibility": "public"}, {"name": "fetchPath", "visibility": "public"}, {"name": "", "parameters": ["uuid"], "visibility": "public"}, {"name": "fetchEntry", "visibility": "public"}, {"name": "awaitStableEntry", "visibility": "public"}, {"name": "fetchSubdomains", "parameters": ["user", "_force"], "visibility": "public"}, {"name": "applySingleSubdomain", "parameters": ["sd"], "visibility": "public"}, {"name": "fetchOwner", "parameters": ["_force"], "visibility": "public"}]}, {"name": "PermissionService", "kind": "class", "source_file": "data/acc878f9-aeca-493c-bc04-48fb2d22d115/src/backend/src/services/auth/PermissionService.js", "methods": [{"name": "_construct", "visibility": "public"}, {"name": "_init", "visibility": "public"}, {"name": "", "visibility": "public"}, {"name": "_rewrite_permission", "parameters": ["permission"], "visibility": "public"}, {"name": "", "parameters": ["actor", "permission_options", "_reserved", "state"], "visibility": "public"}, {"name": "invalidate_permission_scan_cache_for_app_under_user", "parameters": ["user_uuid", "app_uid", "permission"], "visibility": "public"}, {"name": "validateUserPerms", "visibility": "public"}, {"name": "", "visibility": "public"}, {"name": "", "visibility": "public"}, {"name": "grant_user_app_permission", "parameters": ["actor", "app_uid", "permission", "meta"], "visibility": "public"}, {"name": "grant_dev_app_permission", "parameters": ["actor", "app_uid", "permission", "meta"], "visibility": "public"}, {"name": "revoke_dev_app_permission", "parameters": ["actor", "app_uid", "permission", "meta"], "visibility": "public"}, {"name": "revoke_dev_app_all", "parameters": ["actor", "app_uid", "meta"], "visibility": "public"}, {"name": "revoke_user_app_permission", "parameters": ["actor", "app_uid", "permission", "meta"], "visibility": "public"}, {"name": "revoke_user_app_all", "parameters": ["actor", "app_uid", "meta"], "visibility": "public"}, {"name": "grant_user_user_permission", "parameters": ["actor", "username", "permission", "meta"], "visibility": "public"}, {"name": "", "parameters": ["actor", "user", "permission"], "visibility": "public"}, {"name": "", "parameters": ["actor", "user", "permission", "meta"], "visibility": "public"}, {"name": "grant_user_group_permission", "parameters": ["actor", "gid", "permission", "meta"], "visibility": "public"}, {"name": "revoke_user_user_permission", "parameters": ["actor", "username", "permission", "meta"], "visibility": "public"}]}, {"name": "FSEntryController", "kind": "class", "source_file": "data/acc878f9-aeca-493c-bc04-48fb2d22d115/extensions/legacyFileSystem/fsentries/FSEntryController.js", "methods": [{"name": "constructor", "visibility": "public"}, {"name": "init", "visibility": "public"}, {"name": "mkPromiseForQueueSize_", "visibility": "public"}, {"name": "insert", "parameters": ["entry"], "visibility": "public"}, {"name": "update", "parameters": ["uuid", "entry"], "visibility": "public"}, {"name": "delete", "parameters": ["uuid"], "visibility": "public"}, {"name": "fast_get_descendants", "parameters": ["uuid"], "visibility": "public"}, {"name": "fast_get_direct_descendants", "parameters": ["uuid"], "visibility": "public"}, {"name": "waitForEntry", "parameters": ["node", "callback"], "visibility": "public"}, {"name": "get", "parameters": ["uuid", "fetch_entry_options"], "visibility": "public"}, {"name": "get_descendants", "parameters": ["uuid"], "visibility": "public"}, {"name": "get_descendants_full", "parameters": ["uuid", "fetch_entry_options"], "visibility": "public"}, {"name": "get_recursive_size", "parameters": ["uuid"], "visibility": "public"}, {"name": "find", "parameters": ["selector", "fetch_entry_options"], "visibility": "public"}, {"name": "findByUID", "parameters": ["uuid"], "visibility": "public"}, {"name": "findByID", "parameters": ["id"], "visibility": "public"}, {"name": "findByPath", "parameters": ["path"], "visibility": "public"}, {"name": "findNameInRoot", "parameters": ["name"], "visibility": "public"}, {"name": "findNameInParent", "parameters": ["parent_uid", "name"], "visibility": "public"}, {"name": "nameExistsUnderParent", "parameters": ["parent_uid", "name"], "visibility": "public"}]}, {"name": "FSEntryController", "kind": "class", "source_file": "data/acc878f9-aeca-493c-bc04-48fb2d22d115/extensions/legacyFileSystem/fsentries/FSEntryController.js", "methods": [{"name": "constructor", "visibility": "public"}, {"name": "init", "visibility": "public"}, {"name": "mkPromiseForQueueSize_", "visibility": "public"}, {"name": "insert", "parameters": ["entry"], "visibility": "public"}, {"name": "update", "parameters": ["uuid", "entry"], "visibility": "public"}, {"name": "delete", "parameters": ["uuid"], "visibility": "public"}, {"name": "fast_get_descendants", "parameters": ["uuid"], "visibility": "public"}, {"name": "fast_get_direct_descendants", "parameters": ["uuid"], "visibility": "public"}, {"name": "waitForEntry", "parameters": ["node", "callback"], "visibility": "public"}, {"name": "get", "parameters": ["uuid", "fetch_entry_options"], "visibility": "public"}, {"name": "get_descendants", "parameters": ["uuid"], "visibility": "public"}, {"name": "get_descendants_full", "parameters": ["uuid", "fetch_entry_options"], "visibility": "public"}, {"name": "get_recursive_size", "parameters": ["uuid"], "visibility": "public"}, {"name": "find", "parameters": ["selector", "fetch_entry_options"], "visibility": "public"}, {"name": "findByUID", "parameters": ["uuid"], "visibility": "public"}, {"name": "findByID", "parameters": ["id"], "visibility": "public"}, {"name": "findByPath", "parameters": ["path"], "visibility": "public"}, {"name": "findNameInRoot", "parameters": ["name"], "visibility": "public"}, {"name": "findNameInParent", "parameters": ["parent_uid", "name"], "visibility": "public"}, {"name": "nameExistsUnderParent", "parameters": ["parent_uid", "name"], "visibility": "public"}]}, {"name": "PuterFSProvider", "kind": "class", "source_file": "data/acc878f9-aeca-493c-bc04-48fb2d22d115/extensions/legacyFileSystem/PuterFSProvider.js", "methods": [{"name": "constructor", "visibility": "public"}, {"name": "", "parameters": ["path"], "visibility": "public"}, {"name": "", "parameters": ["node"], "visibility": "public"}, {"name": "", "parameters": ["destinationPathDepth", "sourceNode"], "visibility": "public"}, {"name": "get_capabilities", "visibility": "public"}, {"name": "update_thumbnail", "visibility": "public"}, {"name": "puter_shortcut", "visibility": "public"}, {"name": "readdirstat_uuid", "visibility": "public"}, {"name": "quick_check", "visibility": "public"}, {"name": "unlink", "visibility": "public"}, {"name": "rmdir", "visibility": "public"}, {"name": "mkdir", "visibility": "public"}, {"name": "read", "visibility": "public"}, {"name": "stat", "visibility": "public"}, {"name": "copy_tree", "visibility": "public"}, {"name": "move", "visibility": "public"}, {"name": "readdir", "visibility": "public"}, {"name": "directory_has_name", "visibility": "public"}, {"name": "write_new", "visibility": "public"}, {"name": "write_overwrite", "visibility": "public"}]}, {"name": "PuterFSProvider", "kind": "class", "source_file": "data/acc878f9-aeca-493c-bc04-48fb2d22d115/extensions/legacyFileSystem/PuterFSProvider.js", "methods": [{"name": "constructor", "visibility": "public"}, {"name": "", "parameters": ["path"], "visibility": "public"}, {"name": "", "parameters": ["node"], "visibility": "public"}, {"name": "", "parameters": ["destinationPathDepth", "sourceNode"], "visibility": "public"}, {"name": "get_capabilities", "visibility": "public"}, {"name": "update_thumbnail", "visibility": "public"}, {"name": "puter_shortcut", "visibility": "public"}, {"name": "readdirstat_uuid", "visibility": "public"}, {"name": "quick_check", "visibility": "public"}, {"name": "unlink", "visibility": "public"}, {"name": "rmdir", "visibility": "public"}, {"name": "mkdir", "visibility": "public"}, {"name": "read", "visibility": "public"}, {"name": "stat", "visibility": "public"}, {"name": "copy_tree", "visibility": "public"}, {"name": "move", "visibility": "public"}, {"name": "readdir", "visibility": "public"}, {"name": "directory_has_name", "visibility": "public"}, {"name": "write_new", "visibility": "public"}, {"name": "write_overwrite", "visibility": "public"}]}, {"name": "AIImageGenerationService", "kind": "class", "source_file": "data/acc878f9-aeca-493c-bc04-48fb2d22d115/src/backend/src/services/ai/image/AIImageGenerationService.ts", "methods": [{"name": "meteringService", "visibility": "public"}, {"name": "db", "visibility": "public"}, {"name": "errorService", "visibility": "public"}, {"name": "eventService", "visibility": "public"}, {"name": "driverService", "visibility": "public"}, {"name": "getProvider", "parameters": ["string"], "visibility": "public"}, {"name": "getModel", "visibility": "public"}, {"name": "registerProviders", "visibility": "public"}, {"name": "", "visibility": "public"}, {"name": "models", "visibility": "public"}, {"name": "list", "visibility": "public"}, {"name": "generate", "parameters": ["IGenerateParams"], "visibility": "public"}, {"name": "if", "visibility": "public"}, {"name": "if", "visibility": "public"}, {"name": "if", "visibility": "public"}, {"name": "if", "visibility": "public"}, {"name": "if", "visibility": "public"}, {"name": "if", "visibility": "public"}, {"name": "if", "visibility": "public"}, {"name": "if", "visibility": "public"}]}, {"name": "AIImageGenerationService", "kind": "class", "source_file": "data/acc878f9-aeca-493c-bc04-48fb2d22d115/src/backend/src/services/ai/image/AIImageGenerationService.ts", "methods": [{"name": "meteringService", "visibility": "public"}, {"name": "db", "visibility": "public"}, {"name": "errorService", "visibility": "public"}, {"name": "eventService", "visibility": "public"}, {"name": "driverService", "visibility": "public"}, {"name": "getProvider", "parameters": ["string"], "visibility": "public"}, {"name": "getModel", "visibility": "public"}, {"name": "registerProviders", "visibility": "public"}, {"name": "", "visibility": "public"}, {"name": "models", "visibility": "public"}, {"name": "list", "visibility": "public"}, {"name": "generate", "parameters": ["IGenerateParams"], "visibility": "public"}, {"name": "if", "visibility": "public"}, {"name": "if", "visibility": "public"}, {"name": "if", "visibility": "public"}, {"name": "if", "visibility": "public"}, {"name": "if", "visibility": "public"}, {"name": "if", "visibility": "public"}, {"name": "if", "visibility": "public"}, {"name": "if", "visibility": "public"}]}, {"name": "Extension", "kind": "class", "source_file": "data/acc878f9-aeca-493c-bc04-48fb2d22d115/src/backend/src/Extension.js", "methods": [{"name": "constructor", "visibility": "public"}, {"name": "randomBrightColor", "visibility": "public"}, {"name": "ample (", "visibility": "public"}, {"name": "ports (", "parameters": ["lue)"], "visibility": "public"}, {"name": "ports (", "visibility": "public"}, {"name": "port (", "parameters": ["me)"], "visibility": "public"}, {"name": "(", "visibility": "public"}, {"name": "rvices (", "visibility": "public"}, {"name": "g_context (", "visibility": "public"}, {"name": "rors (", "visibility": "public"}, {"name": "gister (", "parameters": ["peKey,", "yOrData,", "ta)"], "visibility": "public"}, {"name": "g (", "visibility": "public"}, {"name": "t (", "parameters": ["th,", "ndler,", "tions)"], "visibility": "public"}, {"name": "st (", "parameters": ["th,", "ndler,", "tions)"], "visibility": "public"}, {"name": "t (", "parameters": ["th,", "ndler,", "tions)"], "visibility": "public"}, {"name": "lete (", "parameters": ["th,", "ndler,", "tions)"], "visibility": "public"}, {"name": "e (", "visibility": "public"}, {"name": "einit (", "visibility": "public"}, {"name": "einit (", "parameters": ["llback)"], "visibility": "public"}, {"name": "it (", "visibility": "public"}]}, {"name": "BroadcastService", "kind": "class", "source_file": "data/acc878f9-aeca-493c-bc04-48fb2d22d115/src/backend/src/modules/broadcast/BroadcastService.js", "methods": [{"name": "_init", "visibility": "public"}, {"name": "outBroadcastEventHandler", "parameters": ["key", "data", "meta"], "visibility": "public"}, {"name": "", "parameters": ["event"], "visibility": "public"}, {"name": "", "parameters": ["event"], "visibility": "public"}, {"name": "", "visibility": "public"}, {"name": "", "visibility": "public"}, {"name": "", "parameters": ["meta"], "visibility": "public"}, {"name": "", "visibility": "public"}, {"name": "", "parameters": ["peerConfig"], "visibility": "public"}, {"name": "", "visibility": "public"}, {"name": "", "visibility": "public"}, {"name": "", "parameters": ["key"], "visibility": "public"}, {"name": "", "parameters": ["events"], "visibility": "public"}, {"name": "", "parameters": ["events"], "visibility": "public"}, {"name": "", "parameters": ["channel", "message"], "visibility": "public"}, {"name": "", "parameters": ["payload"], "visibility": "public"}, {"name": "", "parameters": ["event"], "visibility": "public"}, {"name": "", "parameters": ["events"], "visibility": "public"}, {"name": "", "parameters": ["_"], "visibility": "public"}, {"name": "", "parameters": ["req", "res"], "visibility": "public"}]}, {"name": "BroadcastService", "kind": "class", "source_file": "data/acc878f9-aeca-493c-bc04-48fb2d22d115/src/backend/src/modules/broadcast/BroadcastService.js", "methods": [{"name": "_init", "visibility": "public"}, {"name": "outBroadcastEventHandler", "parameters": ["key", "data", "meta"], "visibility": "public"}, {"name": "", "parameters": ["event"], "visibility": "public"}, {"name": "", "parameters": ["event"], "visibility": "public"}, {"name": "", "visibility": "public"}, {"name": "", "visibility": "public"}, {"name": "", "parameters": ["meta"], "visibility": "public"}, {"name": "", "visibility": "public"}, {"name": "", "parameters": ["peerConfig"], "visibility": "public"}, {"name": "", "visibility": "public"}, {"name": "", "visibility": "public"}, {"name": "", "parameters": ["key"], "visibility": "public"}, {"name": "", "parameters": ["events"], "visibility": "public"}, {"name": "", "parameters": ["events"], "visibility": "public"}, {"name": "", "parameters": ["channel", "message"], "visibility": "public"}, {"name": "", "parameters": ["payload"], "visibility": "public"}, {"name": "", "parameters": ["event"], "visibility": "public"}, {"name": "", "parameters": ["events"], "visibility": "public"}, {"name": "", "parameters": ["_"], "visibility": "public"}, {"name": "", "parameters": ["req", "res"], "visibility": "public"}]}, {"name": "wt", "kind": "class", "source_file": "data/acc878f9-aeca-493c-bc04-48fb2d22d115/src/gui/src/lib/socket.io/socket.io.esm.min.js", "methods": [{"name": "constructor", "parameters": ["t", "e"], "visibility": "public"}, {"name": "reconnection", "parameters": ["t"], "visibility": "public"}, {"name": "reconnectionAttempts", "parameters": ["t"], "visibility": "public"}, {"name": "reconnectionDelay", "parameters": ["t"], "visibility": "public"}, {"name": "randomizationFactor", "parameters": ["t"], "visibility": "public"}, {"name": "reconnectionDelayMax", "parameters": ["t"], "visibility": "public"}, {"name": "timeout", "parameters": ["t"], "visibility": "public"}, {"name": "maybeReconnectOnOpen", "visibility": "public"}, {"name": "open", "parameters": ["t"], "visibility": "public"}, {"name": "connect", "parameters": ["t"], "visibility": "public"}, {"name": "onopen", "visibility": "public"}, {"name": "onping", "visibility": "public"}, {"name": "ondata", "parameters": ["t"], "visibility": "public"}, {"name": "ondecoded", "parameters": ["t"], "visibility": "public"}, {"name": "onerror", "parameters": ["t"], "visibility": "public"}, {"name": "socket", "parameters": ["t", "e"], "visibility": "public"}, {"name": "_destroy", "parameters": ["t"], "visibility": "public"}, {"name": "_packet", "parameters": ["t"], "visibility": "public"}, {"name": "cleanup", "visibility": "public"}, {"name": "_close", "visibility": "public"}]}, {"name": "wt", "kind": "class", "source_file": "data/acc878f9-aeca-493c-bc04-48fb2d22d115/src/puter-js/src/lib/socket.io/socket.io.esm.min.js", "methods": [{"name": "constructor", "parameters": ["t", "e"], "visibility": "public"}, {"name": "reconnection", "parameters": ["t"], "visibility": "public"}, {"name": "reconnectionAttempts", "parameters": ["t"], "visibility": "public"}, {"name": "reconnectionDelay", "parameters": ["t"], "visibility": "public"}, {"name": "randomizationFactor", "parameters": ["t"], "visibility": "public"}, {"name": "reconnectionDelayMax", "parameters": ["t"], "visibility": "public"}, {"name": "timeout", "parameters": ["t"], "visibility": "public"}, {"name": "maybeReconnectOnOpen", "visibility": "public"}, {"name": "open", "parameters": ["t"], "visibility": "public"}, {"name": "connect", "parameters": ["t"], "visibility": "public"}, {"name": "onopen", "visibility": "public"}, {"name": "onping", "visibility": "public"}, {"name": "ondata", "parameters": ["t"], "visibility": "public"}, {"name": "ondecoded", "parameters": ["t"], "visibility": "public"}, {"name": "onerror", "parameters": ["t"], "visibility": "public"}, {"name": "socket", "parameters": ["t", "e"], "visibility": "public"}, {"name": "_destroy", "parameters": ["t"], "visibility": "public"}, {"name": "_packet", "parameters": ["t"], "visibility": "public"}, {"name": "cleanup", "visibility": "public"}, {"name": "_close", "visibility": "public"}]}, {"name": "AIVideoGenerationService", "kind": "class", "source_file": "data/acc878f9-aeca-493c-bc04-48fb2d22d115/src/backend/src/services/ai/video/AIVideoGenerationService.ts", "methods": [{"name": "meteringService", "visibility": "public"}, {"name": "eventService", "visibility": "public"}, {"name": "driverService", "visibility": "public"}, {"name": "getProvider", "parameters": ["string"], "visibility": "public"}, {"name": "getModel", "visibility": "public"}, {"name": "registerProviders", "visibility": "public"}, {"name": "", "visibility": "public"}, {"name": "models", "visibility": "public"}, {"name": "list", "visibility": "public"}, {"name": "generate", "parameters": ["IGenerateVideoParams"], "visibility": "public"}, {"name": "if", "visibility": "public"}, {"name": "if", "visibility": "public"}, {"name": "if", "visibility": "public"}, {"name": "if", "visibility": "public"}, {"name": "if", "visibility": "public"}, {"name": "if", "visibility": "public"}, {"name": "if", "visibility": "public"}, {"name": "if", "visibility": "public"}, {"name": "if", "visibility": "public"}]}, {"name": "AIVideoGenerationService", "kind": "class", "source_file": "data/acc878f9-aeca-493c-bc04-48fb2d22d115/src/backend/src/services/ai/video/AIVideoGenerationService.ts", "methods": [{"name": "meteringService", "visibility": "public"}, {"name": "eventService", "visibility": "public"}, {"name": "driverService", "visibility": "public"}, {"name": "getProvider", "parameters": ["string"], "visibility": "public"}, {"name": "getModel", "visibility": "public"}, {"name": "registerProviders", "visibility": "public"}, {"name": "", "visibility": "public"}, {"name": "models", "visibility": "public"}, {"name": "list", "visibility": "public"}, {"name": "generate", "parameters": ["IGenerateVideoParams"], "visibility": "public"}, {"name": "if", "visibility": "public"}, {"name": "if", "visibility": "public"}, {"name": "if", "visibility": "public"}, {"name": "if", "visibility": "public"}, {"name": "if", "visibility": "public"}, {"name": "if", "visibility": "public"}, {"name": "if", "visibility": "public"}, {"name": "if", "visibility": "public"}, {"name": "if", "visibility": "public"}]}, {"name": "DriverService", "kind": "class", "source_file": "data/acc878f9-aeca-493c-bc04-48fb2d22d115/src/backend/src/services/drivers/DriverService.js", "methods": [{"name": "_construct", "visibility": "public"}, {"name": "_init", "visibility": "public"}, {"name": "", "visibility": "public"}, {"name": "", "visibility": "public"}, {"name": "", "visibility": "public"}, {"name": "", "visibility": "public"}, {"name": "register_driver", "parameters": ["interface_name", "implementation"], "visibility": "public"}, {"name": "register_test_service", "parameters": ["interface_name", "service_name"], "visibility": "public"}, {"name": "register_service_alias", "parameters": ["service_name", "alias"], "visibility": "public"}, {"name": "get_default_implementation", "parameters": ["interface_name"], "visibility": "public"}, {"name": "call", "parameters": ["o"], "visibility": "public"}, {"name": "_call", "visibility": "public"}, {"name": "get_policies_for_option_", "parameters": ["option"], "visibility": "public"}, {"name": "select_best_option_", "parameters": ["options"], "visibility": "public"}, {"name": "call_new_", "visibility": "public"}, {"name": "_driver_response_from_error", "parameters": ["e", "meta"], "visibility": "public"}, {"name": "_process_args", "parameters": ["interface_name", "method_name", "args"], "visibility": "public"}, {"name": "get_service_or_throw_", "parameters": ["name", "iface"], "visibility": "public"}]}, {"name": "X", "kind": "class", "source_file": "data/acc878f9-aeca-493c-bc04-48fb2d22d115/src/gui/src/lib/socket.io/socket.io.esm.min.js", "methods": [{"name": "constructor", "parameters": ["t"], "visibility": "public"}, {"name": "createTransport", "parameters": ["t"], "visibility": "public"}, {"name": "open", "visibility": "public"}, {"name": "setTransport", "parameters": ["t"], "visibility": "public"}, {"name": "probe", "parameters": ["t"], "visibility": "public"}, {"name": "onOpen", "visibility": "public"}, {"name": "onPacket", "parameters": ["t"], "visibility": "public"}, {"name": "onHandshake", "parameters": ["t"], "visibility": "public"}, {"name": "resetPingTimeout", "visibility": "public"}, {"name": "onDrain", "visibility": "public"}, {"name": "flush", "visibility": "public"}, {"name": "getWritablePackets", "visibility": "public"}, {"name": "write", "parameters": ["t", "e", "s"], "visibility": "public"}, {"name": "send", "parameters": ["t", "e", "s"], "visibility": "public"}, {"name": "sendPacket", "parameters": ["t", "e", "s", "n"], "visibility": "public"}, {"name": "close", "visibility": "public"}, {"name": "onError", "parameters": ["t"], "visibility": "public"}, {"name": "onClose", "parameters": ["t", "e"], "visibility": "public"}, {"name": "filterUpgrades", "parameters": ["t"], "visibility": "public"}]}, {"name": "SessionService", "kind": "class", "source_file": "data/acc878f9-aeca-493c-bc04-48fb2d22d115/src/backend/src/services/SessionService.js", "methods": [{"name": "getSessionCacheKey", "parameters": ["uuid"], "visibility": "public"}, {"name": "getSessionUserSetKey", "parameters": ["userId"], "visibility": "public"}, {"name": "getSessionFlushLockKey", "parameters": ["uuid"], "visibility": "public"}, {"name": "", "visibility": "public"}, {"name": "", "visibility": "public"}, {"name": "cacheSession", "parameters": ["session"], "visibility": "public"}, {"name": "getCachedSession", "parameters": ["uuid"], "visibility": "public"}, {"name": "invalidateCachedSession", "parameters": ["uuid", "userId"], "visibility": "public"}, {"name": "_init", "visibility": "public"}, {"name": "create_session", "parameters": ["user", "meta"], "visibility": "public"}, {"name": "", "parameters": ["uuid"], "visibility": "public"}, {"name": "getSession", "parameters": ["uuid"], "visibility": "public"}, {"name": "", "parameters": ["session"], "visibility": "public"}, {"name": "get_user_sessions", "parameters": ["user"], "visibility": "public"}, {"name": "remove_session", "parameters": ["uuid"], "visibility": "public"}, {"name": "", "visibility": "public"}]}, {"name": "X", "kind": "class", "source_file": "data/acc878f9-aeca-493c-bc04-48fb2d22d115/src/puter-js/src/lib/socket.io/socket.io.esm.min.js", "methods": [{"name": "constructor", "parameters": ["t"], "visibility": "public"}, {"name": "createTransport", "parameters": ["t"], "visibility": "public"}, {"name": "open", "visibility": "public"}, {"name": "setTransport", "parameters": ["t"], "visibility": "public"}, {"name": "probe", "parameters": ["t"], "visibility": "public"}, {"name": "onOpen", "visibility": "public"}, {"name": "onPacket", "parameters": ["t"], "visibility": "public"}, {"name": "onHandshake", "parameters": ["t"], "visibility": "public"}, {"name": "resetPingTimeout", "visibility": "public"}, {"name": "onDrain", "visibility": "public"}, {"name": "flush", "visibility": "public"}, {"name": "getWritablePackets", "visibility": "public"}, {"name": "write", "parameters": ["t", "e", "s"], "visibility": "public"}, {"name": "send", "parameters": ["t", "e", "s"], "visibility": "public"}, {"name": "sendPacket", "parameters": ["t", "e", "s", "n"], "visibility": "public"}, {"name": "close", "visibility": "public"}, {"name": "onError", "parameters": ["t"], "visibility": "public"}, {"name": "onClose", "parameters": ["t", "e"], "visibility": "public"}, {"name": "filterUpgrades", "parameters": ["t"], "visibility": "public"}]}, {"name": "AppInformationService", "kind": "class", "source_file": "data/acc878f9-aeca-493c-bc04-48fb2d22d115/src/backend/src/modules/apps/AppInformationService.js", "methods": [{"name": "_construct", "visibility": "public"}, {"name": "", "visibility": "public"}, {"name": "invalidateAppCache", "visibility": "public"}, {"name": "get_stats", "parameters": ["app_uid"], "visibility": "public"}, {"name": "_refresh_app_stats", "visibility": "public"}, {"name": "_refresh_app_stat_referrals", "visibility": "public"}, {"name": "delete_app", "parameters": ["app_uid", "app"], "visibility": "public"}, {"name": "buildCanonicalAppUidAliasKey_", "parameters": ["appUid"], "visibility": "public"}, {"name": "buildCanonicalAppUidAliasReverseKey_", "parameters": ["canonicalAppUid"], "visibility": "public"}, {"name": "normalizeCanonicalAliasUidList_", "parameters": ["value"], "visibility": "public"}, {"name": "cleanupCanonicalAppUidAliases_", "parameters": ["appUid"], "visibility": "public"}, {"name": "generateAllPeriods", "parameters": ["startDate", "endDate", "grouping"], "visibility": "public"}, {"name": "getWeekNumber", "parameters": ["date"], "visibility": "public"}, {"name": "mergeWithGeneratedPeriods", "parameters": ["actualData", "allPeriods", "stats_grouping"], "visibility": "public"}]}, {"name": "OIDCService", "kind": "class", "source_file": "data/acc878f9-aeca-493c-bc04-48fb2d22d115/src/backend/src/services/auth/OIDCService.js", "methods": [{"name": "_init", "visibility": "public"}, {"name": "getProviderConfig", "parameters": ["providerId"], "visibility": "public"}, {"name": "", "visibility": "public"}, {"name": "getCallbackUrlForFlow", "parameters": ["flow"], "visibility": "public"}, {"name": "getAuthorizationUrl", "parameters": ["providerId", "state", "flow"], "visibility": "public"}, {"name": "signState", "parameters": ["payload"], "visibility": "public"}, {"name": "verifyState", "parameters": ["token"], "visibility": "public"}, {"name": "exchangeCodeForTokens", "parameters": ["providerId", "code", "redirectUri"], "visibility": "public"}, {"name": "getUserInfo", "parameters": ["providerId", "accessToken"], "visibility": "public"}, {"name": "findUserByProviderSub", "parameters": ["providerId", "providerSub"], "visibility": "public"}, {"name": "linkProviderToUser", "parameters": ["userId", "providerId", "providerSub"], "visibility": "public"}, {"name": "createUserFromOIDC", "parameters": ["providerId", "claims"], "visibility": "public"}, {"name": "getEnabledProviderIds", "visibility": "public"}]}, {"name": "OIDCService", "kind": "class", "source_file": "data/acc878f9-aeca-493c-bc04-48fb2d22d115/src/backend/src/services/auth/OIDCService.js", "methods": [{"name": "_init", "visibility": "public"}, {"name": "getProviderConfig", "parameters": ["providerId"], "visibility": "public"}, {"name": "", "visibility": "public"}, {"name": "getCallbackUrlForFlow", "parameters": ["flow"], "visibility": "public"}, {"name": "getAuthorizationUrl", "parameters": ["providerId", "state", "flow"], "visibility": "public"}, {"name": "signState", "parameters": ["payload"], "visibility": "public"}, {"name": "verifyState", "parameters": ["token"], "visibility": "public"}, {"name": "exchangeCodeForTokens", "parameters": ["providerId", "code", "redirectUri"], "visibility": "public"}, {"name": "getUserInfo", "parameters": ["providerId", "accessToken"], "visibility": "public"}, {"name": "findUserByProviderSub", "parameters": ["providerId", "providerSub"], "visibility": "public"}, {"name": "linkProviderToUser", "parameters": ["userId", "providerId", "providerSub"], "visibility": "public"}, {"name": "createUserFromOIDC", "parameters": ["providerId", "claims"], "visibility": "public"}, {"name": "getEnabledProviderIds", "visibility": "public"}]}, {"name": "ServerHealthService", "kind": "class", "source_file": "data/acc878f9-aeca-493c-bc04-48fb2d22d115/src/backend/src/modules/core/ServerHealthService/ServerHealthService.js", "methods": [{"name": "_construct", "visibility": "public"}, {"name": "_init", "visibility": "public"}, {"name": "", "visibility": "public"}, {"name": "beginDrain", "visibility": "public"}, {"name": "", "visibility": "public"}, {"name": "", "visibility": "public"}, {"name": "", "visibility": "public"}, {"name": "get_stats", "visibility": "public"}, {"name": "add_check", "parameters": ["name", "fn"], "visibility": "public"}, {"name": "get_status", "visibility": "public"}, {"name": "", "visibility": "public"}, {"name": "", "visibility": "public"}, {"name": "", "parameters": ["serviceName"], "visibility": "public"}]}, {"name": "HostDiskUsageService", "kind": "class", "source_file": "data/acc878f9-aeca-493c-bc04-48fb2d22d115/src/backend/src/services/HostDiskUsageService.js", "methods": [{"name": "_init", "visibility": "public"}, {"name": "get_host_usage", "visibility": "public"}, {"name": "get_extra", "visibility": "public"}, {"name": "get_darwin_mountpoint", "parameters": ["directory"], "visibility": "public"}, {"name": "get_linux_mountpint", "parameters": ["directory"], "visibility": "public"}, {"name": "get_windows_drive", "parameters": ["directory"], "visibility": "public"}, {"name": "get_disk_capacity_darwin", "parameters": ["mountpoint"], "visibility": "public"}, {"name": "get_disk_capacity_linux", "parameters": ["mountpoint"], "visibility": "public"}, {"name": "get_disk_capacity_windows", "parameters": ["drive"], "visibility": "public"}, {"name": "get_disk_use_darwin", "parameters": ["mountpoint"], "visibility": "public"}, {"name": "get_disk_use_linux", "parameters": ["mountpoint"], "visibility": "public"}, {"name": "get_disk_use_windows", "parameters": ["drive"], "visibility": "public"}]}, {"name": "LogContext", "kind": "class", "source_file": "data/acc878f9-aeca-493c-bc04-48fb2d22d115/src/backend/src/modules/core/LogService.js", "methods": [{"name": "constructor", "parameters": ["logService"], "visibility": "public"}, {"name": "sub", "parameters": ["name"], "visibility": "public"}, {"name": "info", "parameters": ["message", "fields", "objects"], "visibility": "public"}, {"name": "warn", "parameters": ["message", "fields", "objects"], "visibility": "public"}, {"name": "debug", "parameters": ["message", "fields", "objects"], "visibility": "public"}, {"name": "error", "parameters": ["message", "fields", "objects"], "visibility": "public"}, {"name": "tick", "parameters": ["message", "fields", "objects"], "visibility": "public"}, {"name": "called", "visibility": "public"}, {"name": "noticeme", "parameters": ["message", "fields", "objects"], "visibility": "public"}, {"name": "system", "parameters": ["message", "fields", "objects"], "visibility": "public"}, {"name": "cache", "parameters": ["isCacheHit", "identifier"], "visibility": "public"}, {"name": "log", "parameters": ["log_level", "message"], "visibility": "public"}, {"name": "mkid", "visibility": "public"}, {"name": "traceOn", "visibility": "public"}, {"name": "get_log_buffer", "visibility": "public"}]}, {"name": "CaptchaService", "kind": "class", "source_file": "data/acc878f9-aeca-493c-bc04-48fb2d22d115/src/backend/src/modules/captcha/services/CaptchaService.js", "methods": [{"name": "_construct", "visibility": "public"}, {"name": "", "parameters": ["_"], "visibility": "public"}, {"name": "_init", "visibility": "public"}, {"name": "_destroy", "visibility": "public"}, {"name": "registerEndpoints", "visibility": "public"}, {"name": "generateCaptcha", "visibility": "public"}, {"name": "verifyCaptcha", "parameters": ["token", "userAnswer"], "visibility": "public"}, {"name": "_checkServiceHealth", "visibility": "public"}, {"name": "cleanupExpiredTokens", "visibility": "public"}, {"name": "_getCaptchaOptions", "visibility": "public"}, {"name": "verifySelfTest", "visibility": "public"}, {"name": "getDiagnosticInfo", "visibility": "public"}]}, {"name": "C", "kind": "class", "source_file": "data/acc878f9-aeca-493c-bc04-48fb2d22d115/src/gui/src/lib/socket.io/socket.io.esm.min.js", "methods": [{"name": "constructor", "parameters": ["t"], "visibility": "public"}, {"name": "onError", "parameters": ["t", "e", "s"], "visibility": "public"}, {"name": "open", "visibility": "public"}, {"name": "close", "visibility": "public"}, {"name": "send", "parameters": ["t"], "visibility": "public"}, {"name": "onOpen", "visibility": "public"}, {"name": "onData", "parameters": ["t"], "visibility": "public"}, {"name": "onPacket", "parameters": ["t"], "visibility": "public"}, {"name": "onClose", "parameters": ["t"], "visibility": "public"}, {"name": "pause", "parameters": ["t"], "visibility": "public"}, {"name": "createUri", "parameters": ["t"], "visibility": "public"}, {"name": "_hostname", "visibility": "public"}, {"name": "_port", "visibility": "public"}, {"name": "_query", "parameters": ["t"], "visibility": "public"}]}, {"name": "Container", "kind": "class", "source_file": "data/acc878f9-aeca-493c-bc04-48fb2d22d115/src/backend/src/services/Container.js", "methods": [{"name": "constructor", "visibility": "public"}, {"name": "registerEnforcer", "parameters": ["func"], "visibility": "public"}, {"name": "registerModule", "parameters": ["name", "module"], "visibility": "public"}, {"name": "setModuleName", "parameters": ["name"], "visibility": "public"}, {"name": "registerService", "parameters": ["name", "cls", "args"], "visibility": "public"}, {"name": "patchService", "parameters": ["name", "patch", "args"], "visibility": "public"}, {"name": "get_implementors", "parameters": ["interface_name"], "visibility": "public"}, {"name": "set", "parameters": ["name", "instance"], "visibility": "public"}, {"name": "_get", "parameters": ["name", "opts"], "visibility": "public"}, {"name": "get", "parameters": ["name", "opts"], "visibility": "public"}, {"name": "has", "parameters": ["name"], "visibility": "public"}, {"name": "values", "visibility": "public"}, {"name": "init", "visibility": "public"}, {"name": "emit", "parameters": ["id"], "visibility": "public"}]}, {"name": "MistralOCRService", "kind": "class", "source_file": "data/acc878f9-aeca-493c-bc04-48fb2d22d115/src/backend/src/services/ai/ocr/MistralOCRService.js", "methods": [{"name": "_init", "visibility": "public"}, {"name": "recognize", "visibility": "public"}, {"name": "_buildDocumentChunkFromSource", "parameters": ["fileFacade"], "visibility": "public"}, {"name": "_safeFileValue", "parameters": ["fileFacade", "key"], "visibility": "public"}, {"name": "_chunkFromUrl", "parameters": ["url", "fileName", "mimeType"], "visibility": "public"}, {"name": "_inferMimeFromName", "parameters": ["name"], "visibility": "public"}, {"name": "_extractMimeFromDataUrl", "parameters": ["url"], "visibility": "public"}, {"name": "_createDataUrl", "parameters": ["buffer", "mimeType"], "visibility": "public"}, {"name": "", "parameters": ["response"], "visibility": "public"}, {"name": "", "parameters": ["response", "model"], "visibility": "public"}, {"name": "", "visibility": "public"}]}, {"name": "MistralOCRService", "kind": "class", "source_file": "data/acc878f9-aeca-493c-bc04-48fb2d22d115/src/backend/src/services/ai/ocr/MistralOCRService.js", "methods": [{"name": "_init", "visibility": "public"}, {"name": "recognize", "visibility": "public"}, {"name": "_buildDocumentChunkFromSource", "parameters": ["fileFacade"], "visibility": "public"}, {"name": "_safeFileValue", "parameters": ["fileFacade", "key"], "visibility": "public"}, {"name": "_chunkFromUrl", "parameters": ["url", "fileName", "mimeType"], "visibility": "public"}, {"name": "_inferMimeFromName", "parameters": ["name"], "visibility": "public"}, {"name": "_extractMimeFromDataUrl", "parameters": ["url"], "visibility": "public"}, {"name": "_createDataUrl", "parameters": ["buffer", "mimeType"], "visibility": "public"}, {"name": "", "parameters": ["response"], "visibility": "public"}, {"name": "", "parameters": ["response", "model"], "visibility": "public"}, {"name": "", "visibility": "public"}]}, {"name": "AlarmService", "kind": "class", "source_file": "data/acc878f9-aeca-493c-bc04-48fb2d22d115/src/backend/src/modules/core/AlarmService.js", "methods": [{"name": "_construct", "visibility": "public"}, {"name": "_init", "visibility": "public"}, {"name": "adapt_id_", "parameters": ["id"], "visibility": "public"}, {"name": "beginDrain", "visibility": "public"}, {"name": "create", "parameters": ["id", "message", "fields"], "visibility": "public"}, {"name": "clear", "parameters": ["id"], "visibility": "public"}, {"name": "apply_known_errors_", "parameters": ["alarm"], "visibility": "public"}, {"name": "handle_alarm_repeat_", "parameters": ["alarm"], "visibility": "public"}, {"name": "handle_alarm_on_", "parameters": ["alarm"], "visibility": "public"}, {"name": "handle_alarm_off_", "parameters": ["alarm"], "visibility": "public"}, {"name": "get_alarm", "parameters": ["id"], "visibility": "public"}]}, {"name": "C", "kind": "class", "source_file": "data/acc878f9-aeca-493c-bc04-48fb2d22d115/src/puter-js/src/lib/socket.io/socket.io.esm.min.js", "methods": [{"name": "constructor", "parameters": ["t"], "visibility": "public"}, {"name": "onError", "parameters": ["t", "e", "s"], "visibility": "public"}, {"name": "open", "visibility": "public"}, {"name": "close", "visibility": "public"}, {"name": "send", "parameters": ["t"], "visibility": "public"}, {"name": "onOpen", "visibility": "public"}, {"name": "onData", "parameters": ["t"], "visibility": "public"}, {"name": "onPacket", "parameters": ["t"], "visibility": "public"}, {"name": "onClose", "parameters": ["t"], "visibility": "public"}, {"name": "pause", "parameters": ["t"], "visibility": "public"}, {"name": "createUri", "parameters": ["t"], "visibility": "public"}, {"name": "_hostname", "visibility": "public"}, {"name": "_port", "visibility": "public"}, {"name": "_query", "parameters": ["t"], "visibility": "public"}]}, {"name": "ShareTestService", "kind": "class", "source_file": "data/acc878f9-aeca-493c-bc04-48fb2d22d115/mods/mods_available/kdmod/ShareTestService.js", "methods": [{"name": "_init", "visibility": "public"}, {"name": "runit", "visibility": "public"}, {"name": "setup_", "visibility": "public"}, {"name": "run_scenario_", "parameters": ["scenario"], "visibility": "public"}, {"name": "teardown_", "visibility": "public"}, {"name": "create_test_user_", "parameters": ["username"], "visibility": "public"}, {"name": "delete_test_user_", "parameters": ["username"], "visibility": "public"}, {"name": "", "visibility": "public"}, {"name": "", "visibility": "public"}, {"name": "", "visibility": "public"}, {"name": "", "visibility": "public"}]}, {"name": "AIChatService", "kind": "class", "source_file": "data/acc878f9-aeca-493c-bc04-48fb2d22d115/src/backend/src/services/ai/chat/AIChatService.ts", "methods": [{"name": "meteringService", "visibility": "public"}, {"name": "db", "visibility": "public"}, {"name": "errorService", "visibility": "public"}, {"name": "eventService", "visibility": "public"}, {"name": "driverService", "visibility": "public"}, {"name": "getProvider", "parameters": ["string"], "visibility": "public"}, {"name": "", "parameters": ["rawLimit"], "visibility": "public"}, {"name": "", "visibility": "public"}, {"name": "els ()", "visibility": "public"}, {"name": "t ()", "visibility": "public"}, {"name": "plete (p", "parameters": ["mpleteArguments) {"], "visibility": "public"}]}, {"name": "AIChatService", "kind": "class", "source_file": "data/acc878f9-aeca-493c-bc04-48fb2d22d115/src/backend/src/services/ai/chat/AIChatService.ts", "methods": [{"name": "meteringService", "visibility": "public"}, {"name": "db", "visibility": "public"}, {"name": "errorService", "visibility": "public"}, {"name": "eventService", "visibility": "public"}, {"name": "driverService", "visibility": "public"}, {"name": "getProvider", "parameters": ["string"], "visibility": "public"}, {"name": "", "parameters": ["rawLimit"], "visibility": "public"}, {"name": "", "visibility": "public"}, {"name": "els ()", "visibility": "public"}, {"name": "t ()", "visibility": "public"}, {"name": "plete (p", "parameters": ["mpleteArguments) {"], "visibility": "public"}]}, {"name": "ProcessService", "kind": "class", "source_file": "data/acc878f9-aeca-493c-bc04-48fb2d22d115/src/gui/src/services/ProcessService.js", "methods": [{"name": "_init", "visibility": "public"}, {"name": "", "visibility": "public"}, {"name": "get_init", "visibility": "public"}, {"name": "get_by_uuid", "parameters": ["uuid"], "visibility": "public"}, {"name": "get_children_of", "parameters": ["uuid"], "visibility": "public"}, {"name": "select_by_name", "parameters": ["name"], "visibility": "public"}, {"name": "register", "parameters": ["process"], "visibility": "public"}, {"name": "register_", "parameters": ["process"], "visibility": "public"}, {"name": "attach_to_parent_", "parameters": ["process"], "visibility": "public"}, {"name": "unregister", "parameters": ["uuid"], "visibility": "public"}]}, {"name": "ProcessService", "kind": "class", "source_file": "data/acc878f9-aeca-493c-bc04-48fb2d22d115/src/gui/src/services/ProcessService.js", "methods": [{"name": "_init", "visibility": "public"}, {"name": "", "visibility": "public"}, {"name": "get_init", "visibility": "public"}, {"name": "get_by_uuid", "parameters": ["uuid"], "visibility": "public"}, {"name": "get_children_of", "parameters": ["uuid"], "visibility": "public"}, {"name": "select_by_name", "parameters": ["name"], "visibility": "public"}, {"name": "register", "parameters": ["process"], "visibility": "public"}, {"name": "register_", "parameters": ["process"], "visibility": "public"}, {"name": "attach_to_parent_", "parameters": ["process"], "visibility": "public"}, {"name": "unregister", "parameters": ["uuid"], "visibility": "public"}]}, {"name": "OperationFrame", "kind": "class", "source_file": "data/acc878f9-aeca-493c-bc04-48fb2d22d115/src/backend/src/services/OperationTraceService.js", "methods": [{"name": "constructor", "visibility": "public"}, {"name": "status", "parameters": ["status"], "visibility": "public"}, {"name": "_calc_effective_status", "visibility": "public"}, {"name": "status", "visibility": "public"}, {"name": "tag", "visibility": "public"}, {"name": "attr", "parameters": ["key", "value"], "visibility": "public"}, {"name": "get_attr", "parameters": ["key"], "visibility": "public"}, {"name": "log", "parameters": ["message"], "visibility": "public"}, {"name": "error", "parameters": ["err"], "visibility": "public"}, {"name": "push_child", "parameters": ["frame"], "visibility": "public"}, {"name": "get_root_frame", "visibility": "public"}, {"name": "done", "visibility": "public"}, {"name": "describe", "parameters": ["show_tree", "highlight_frame"], "visibility": "public"}]}, {"name": "PuterS3Service", "kind": "class", "source_file": "data/acc878f9-aeca-493c-bc04-48fb2d22d115/src/backend/src/deprecated/filesystem/PuterS3Service.js", "methods": [{"name": "_init", "visibility": "public"}, {"name": "", "visibility": "public"}, {"name": "_get_client", "parameters": ["region"], "visibility": "public"}, {"name": "create_read_stream", "visibility": "public"}, {"name": "upload_buffer", "visibility": "public"}, {"name": "put_stream", "visibility": "public"}, {"name": "upload_stream", "visibility": "public"}, {"name": "copy_simple", "visibility": "public"}, {"name": "copy_multipart", "visibility": "public"}, {"name": "delete", "visibility": "public"}]}, {"name": "PuterS3Service", "kind": "class", "source_file": "data/acc878f9-aeca-493c-bc04-48fb2d22d115/src/backend/src/deprecated/filesystem/PuterS3Service.js", "methods": [{"name": "_init", "visibility": "public"}, {"name": "", "visibility": "public"}, {"name": "_get_client", "parameters": ["region"], "visibility": "public"}, {"name": "create_read_stream", "visibility": "public"}, {"name": "upload_buffer", "visibility": "public"}, {"name": "put_stream", "visibility": "public"}, {"name": "upload_stream", "visibility": "public"}, {"name": "copy_simple", "visibility": "public"}, {"name": "copy_multipart", "visibility": "public"}, {"name": "delete", "visibility": "public"}]}, {"name": "ACLService", "kind": "class", "source_file": "data/acc878f9-aeca-493c-bc04-48fb2d22d115/src/backend/src/services/auth/ACLService.js", "methods": [{"name": "_init", "visibility": "public"}, {"name": "check", "parameters": ["actor", "resource", "mode"], "visibility": "public"}, {"name": "", "parameters": ["_"], "visibility": "public"}, {"name": "set_user_user", "parameters": ["issuer", "holder", "resource", "mode"], "visibility": "public"}, {"name": "stat_user_user", "parameters": ["issuer", "holder", "resource"], "visibility": "public"}, {"name": "_check_fsNode", "parameters": ["actor", "fsNode", "mode"], "visibility": "public"}, {"name": "checkResource", "parameters": ["actor", "resource", "mode"], "visibility": "public"}, {"name": "get_safe_acl_error", "parameters": ["actor", "resource", "_mode"], "visibility": "public"}, {"name": "get_highest_mode", "visibility": "public"}, {"name": "_higher_modes", "parameters": ["mode"], "visibility": "public"}]}, {"name": "TelemetryService", "kind": "class", "source_file": "data/acc878f9-aeca-493c-bc04-48fb2d22d115/src/backend/src/modules/perfmon/TelemetryService.js", "methods": [{"name": "constructor", "parameters": ["service_resources"], "visibility": "public"}, {"name": "_init", "visibility": "public"}, {"name": "", "parameters": ["route"], "visibility": "public"}, {"name": "", "parameters": ["req", "route"], "visibility": "public"}, {"name": "", "parameters": ["span", "req", "route"], "visibility": "public"}, {"name": "", "visibility": "public"}, {"name": "", "parameters": ["_serviceConfig"], "visibility": "public"}, {"name": "", "parameters": ["serviceConfig"], "visibility": "public"}, {"name": "", "parameters": ["serviceConfig"], "visibility": "public"}, {"name": "", "visibility": "public"}]}, {"name": "TelemetryService", "kind": "class", "source_file": "data/acc878f9-aeca-493c-bc04-48fb2d22d115/src/backend/src/modules/perfmon/TelemetryService.js", "methods": [{"name": "constructor", "parameters": ["service_resources"], "visibility": "public"}, {"name": "_init", "visibility": "public"}, {"name": "", "parameters": ["route"], "visibility": "public"}, {"name": "", "parameters": ["req", "route"], "visibility": "public"}, {"name": "", "parameters": ["span", "req", "route"], "visibility": "public"}, {"name": "", "visibility": "public"}, {"name": "", "parameters": ["_serviceConfig"], "visibility": "public"}, {"name": "", "parameters": ["serviceConfig"], "visibility": "public"}, {"name": "", "parameters": ["serviceConfig"], "visibility": "public"}, {"name": "", "visibility": "public"}]}, {"name": "WebServerService", "kind": "class", "source_file": "data/acc878f9-aeca-493c-bc04-48fb2d22d115/src/backend/src/modules/web/WebServerService.js", "methods": [{"name": "allow_undefined_origin", "parameters": ["route"], "visibility": "public"}, {"name": "", "visibility": "public"}, {"name": "install_post_middlewares_", "visibility": "public"}, {"name": "", "visibility": "public"}, {"name": "", "visibility": "public"}, {"name": "get_server", "visibility": "public"}, {"name": "registerGracefulShutdownHandlers", "visibility": "public"}, {"name": "beginGracefulShutdown", "parameters": ["signal"], "visibility": "public"}, {"name": "drainCoreServicesForShutdown", "parameters": ["signal"], "visibility": "public"}, {"name": "_init", "visibility": "public"}]}, {"name": "ServiceManager", "kind": "class", "source_file": "data/acc878f9-aeca-493c-bc04-48fb2d22d115/src/putility/src/system/ServiceManager.js", "methods": [{"name": "constructor", "visibility": "public"}, {"name": "register", "parameters": ["name", "factory"], "visibility": "public"}, {"name": "info", "parameters": ["name"], "visibility": "public"}, {"name": "get", "parameters": ["name"], "visibility": "public"}, {"name": "aget", "parameters": ["name"], "visibility": "public"}, {"name": "wait_for_init", "parameters": ["depends"], "visibility": "public"}, {"name": "get_waiting_for_", "parameters": ["depends"], "visibility": "public"}, {"name": "maybe_init_", "parameters": ["name"], "visibility": "public"}, {"name": "init_service_", "parameters": ["name"], "visibility": "public"}]}, {"name": "Kernel", "kind": "class", "source_file": "data/acc878f9-aeca-493c-bc04-48fb2d22d115/src/backend/src/Kernel.js", "methods": [{"name": "constructor", "visibility": "public"}, {"name": "add_module", "parameters": ["module"], "visibility": "public"}, {"name": "_runtime_init", "parameters": ["boot_parameters"], "visibility": "public"}, {"name": "boot", "visibility": "public"}, {"name": "_install_modules", "visibility": "public"}, {"name": "_boot_services", "visibility": "public"}, {"name": "install_extern_mods_", "visibility": "public"}, {"name": "install_extern_mod_", "visibility": "public"}, {"name": "_run_extern_mod", "parameters": ["mod_entry"], "visibility": "public"}, {"name": "_create_mod_context", "parameters": ["parent", "options"], "visibility": "public"}, {"name": "create_mod_package_json", "parameters": ["mod_path"], "visibility": "public"}, {"name": "run_npm_install", "parameters": ["path"], "visibility": "public"}]}, {"name": "ConsoleLogManager", "kind": "class", "source_file": "data/acc878f9-aeca-493c-bc04-48fb2d22d115/src/backend/src/util/consolelog.js", "methods": [{"name": "getInstance", "visibility": "public"}, {"name": "get_log_decorators_", "parameters": ["method"], "visibility": "public"}, {"name": "get_post_hooks_", "parameters": ["method"], "visibility": "public"}, {"name": "constructor", "visibility": "public"}, {"name": "initialize_proxy_methods", "parameters": ["methods"], "visibility": "public"}, {"name": "decorate", "parameters": ["method", "dec_fn"], "visibility": "public"}, {"name": "decorate_all", "parameters": ["dec_fn"], "visibility": "public"}, {"name": "post_all", "parameters": ["post_fn"], "visibility": "public"}, {"name": "log_raw", "parameters": ["method"], "visibility": "public"}]}, {"name": "EntityStoreService", "kind": "class", "source_file": "data/acc878f9-aeca-493c-bc04-48fb2d22d115/src/backend/src/services/EntityStoreService.js", "methods": [{"name": "_init", "parameters": ["args"], "visibility": "public"}, {"name": "create", "parameters": ["entity", "options"], "visibility": "public"}, {"name": "read", "parameters": ["uid"], "visibility": "public"}, {"name": "select", "visibility": "public"}, {"name": "update", "parameters": ["entity", "id", "options"], "visibility": "public"}, {"name": "upsert", "parameters": ["entity", "id", "options"], "visibility": "public"}, {"name": "delete", "parameters": ["uid"], "visibility": "public"}, {"name": "fetch_based_on_complex_id_", "parameters": ["id"], "visibility": "public"}, {"name": "fetch_based_on_either_id_", "parameters": ["uid", "id"], "visibility": "public"}]}, {"name": "WSPushService", "kind": "class", "source_file": "data/acc878f9-aeca-493c-bc04-48fb2d22d115/src/backend/src/services/WSPushService.js", "methods": [{"name": "_init", "visibility": "public"}, {"name": "_on_fs_create", "parameters": ["key", "data"], "visibility": "public"}, {"name": "_on_fs_update", "parameters": ["key", "data"], "visibility": "public"}, {"name": "_on_fs_move", "parameters": ["key", "data"], "visibility": "public"}, {"name": "_on_fs_pending", "parameters": ["key", "data"], "visibility": "public"}, {"name": "_on_upload_progress", "parameters": ["key", "data"], "visibility": "public"}, {"name": "_on_submission_done", "parameters": ["key", "data"], "visibility": "public"}, {"name": "_on_outer_gui", "parameters": ["key", "meta"], "visibility": "public"}, {"name": "_update_user_ts", "parameters": ["user_id_list", "timestamp"], "visibility": "public"}]}, {"name": "SqliteDatabaseAccessService", "kind": "class", "source_file": "data/acc878f9-aeca-493c-bc04-48fb2d22d115/src/backend/src/services/database/SqliteDatabaseAccessService.js", "methods": [{"name": "_init", "visibility": "public"}, {"name": "", "visibility": "public"}, {"name": "_read", "parameters": ["query"], "visibility": "public"}, {"name": "_tryHardRead", "parameters": ["query", "params"], "visibility": "public"}, {"name": "_write", "parameters": ["query", "params"], "visibility": "public"}, {"name": "_batch_write", "parameters": ["entries"], "visibility": "public"}, {"name": "sqlite_transform_query_", "parameters": ["query"], "visibility": "public"}, {"name": "sqlite_transform_params_", "parameters": ["params"], "visibility": "public"}, {"name": "run_js_migration_", "visibility": "public"}]}, {"name": "GroupService", "kind": "class", "source_file": "data/acc878f9-aeca-493c-bc04-48fb2d22d115/src/backend/src/services/auth/GroupService.js", "methods": [{"name": "_init", "visibility": "public"}, {"name": "get", "visibility": "public"}, {"name": "create", "visibility": "public"}, {"name": "list_groups_with_owner", "visibility": "public"}, {"name": "list_groups_with_member", "visibility": "public"}, {"name": "list_public_groups", "visibility": "public"}, {"name": "list_members", "visibility": "public"}, {"name": "add_users", "visibility": "public"}, {"name": "remove_users", "visibility": "public"}]}, {"name": "LogService", "kind": "class", "source_file": "data/acc878f9-aeca-493c-bc04-48fb2d22d115/src/backend/src/modules/core/LogService.js", "methods": [{"name": "_construct", "visibility": "public"}, {"name": "register_log_middleware", "parameters": ["callback"], "visibility": "public"}, {"name": "", "visibility": "public"}, {"name": "_init", "visibility": "public"}, {"name": "create", "parameters": ["prefix"], "visibility": "public"}, {"name": "log_", "parameters": ["log_lvl", "crumbs", "message", "fields", "objects"], "visibility": "public"}, {"name": "ensure_log_directory_", "visibility": "public"}, {"name": "get_log_file", "parameters": ["name"], "visibility": "public"}, {"name": "get_log_buffer", "visibility": "public"}]}, {"name": "Entity", "kind": "class", "source_file": "data/acc878f9-aeca-493c-bc04-48fb2d22d115/src/backend/src/om/entitystorage/Entity.js", "methods": [{"name": "constructor", "parameters": ["args"], "visibility": "public"}, {"name": "create", "parameters": ["args", "data"], "visibility": "public"}, {"name": "clone", "visibility": "public"}, {"name": "apply", "parameters": ["other"], "visibility": "public"}, {"name": "set", "parameters": ["key", "value"], "visibility": "public"}, {"name": "get", "parameters": ["key"], "visibility": "public"}, {"name": "del", "parameters": ["key"], "visibility": "public"}, {"name": "has", "parameters": ["key"], "visibility": "public"}, {"name": "check", "parameters": ["condition"], "visibility": "public"}, {"name": "om_has_property", "parameters": ["key"], "visibility": "public"}, {"name": "is_set", "parameters": ["key"], "visibility": "public"}, {"name": "get_client_safe", "visibility": "public"}]}, {"name": "S3StorageController", "kind": "class", "source_file": "data/acc878f9-aeca-493c-bc04-48fb2d22d115/extensions/legacyFileSystem/storage/S3StorageController.js", "methods": [{"name": "init", "visibility": "public"}, {"name": "", "parameters": ["region"], "visibility": "public"}, {"name": "upload", "visibility": "public"}, {"name": "copy", "visibility": "public"}, {"name": "delete", "visibility": "public"}, {"name": "read", "visibility": "public"}, {"name": "", "visibility": "public"}, {"name": "", "visibility": "public"}, {"name": "", "visibility": "public"}]}, {"name": "S3StorageController", "kind": "class", "source_file": "data/acc878f9-aeca-493c-bc04-48fb2d22d115/extensions/legacyFileSystem/storage/S3StorageController.js", "methods": [{"name": "init", "visibility": "public"}, {"name": "", "parameters": ["region"], "visibility": "public"}, {"name": "upload", "visibility": "public"}, {"name": "copy", "visibility": "public"}, {"name": "delete", "visibility": "public"}, {"name": "read", "visibility": "public"}, {"name": "", "visibility": "public"}, {"name": "", "visibility": "public"}, {"name": "", "visibility": "public"}]}, {"name": "PuterHomepageService", "kind": "class", "source_file": "data/acc878f9-aeca-493c-bc04-48fb2d22d115/src/backend/src/services/PuterHomepageService.js", "methods": [{"name": "_construct", "visibility": "public"}, {"name": "_init", "visibility": "public"}, {"name": "register_script", "parameters": ["url"], "visibility": "public"}, {"name": "set_gui_param", "parameters": ["key", "val"], "visibility": "public"}, {"name": "", "parameters": ["_"], "visibility": "public"}, {"name": "send", "parameters": ["meta", "launch_options"], "visibility": "public"}, {"name": "generate_puter_page_html", "visibility": "public"}, {"name": "generate_error_html", "visibility": "public"}]}, {"name": "PuterHomepageService", "kind": "class", "source_file": "data/acc878f9-aeca-493c-bc04-48fb2d22d115/src/backend/src/services/PuterHomepageService.js", "methods": [{"name": "_construct", "visibility": "public"}, {"name": "_init", "visibility": "public"}, {"name": "register_script", "parameters": ["url"], "visibility": "public"}, {"name": "set_gui_param", "parameters": ["key", "val"], "visibility": "public"}, {"name": "", "parameters": ["_"], "visibility": "public"}, {"name": "send", "parameters": ["meta", "launch_options"], "visibility": "public"}, {"name": "generate_puter_page_html", "visibility": "public"}, {"name": "generate_error_html", "visibility": "public"}]}, {"name": "ReferralCodeService", "kind": "class", "source_file": "data/acc878f9-aeca-493c-bc04-48fb2d22d115/src/backend/src/services/ReferralCodeService.js", "methods": [{"name": "_construct", "visibility": "public"}, {"name": "_init", "visibility": "public"}, {"name": "gen_referral_code", "parameters": ["user"], "visibility": "public"}, {"name": "on_verified", "parameters": ["user"], "visibility": "public"}, {"name": "getMonthlyReferralKey", "parameters": ["referredByUserId"], "visibility": "public"}, {"name": "getNextMonthTimestamp", "visibility": "public"}, {"name": "consumeMonthlyReferralSlot", "parameters": ["referredByUserId"], "visibility": "public"}, {"name": "getUser", "parameters": ["query"], "visibility": "public"}]}, {"name": "AWSPollyService", "kind": "class", "source_file": "data/acc878f9-aeca-493c-bc04-48fb2d22d115/src/backend/src/services/ai/tts/AWSPollyService.js", "methods": [{"name": "meteringService", "visibility": "public"}, {"name": "_construct", "visibility": "public"}, {"name": "_create_aws_credentials", "visibility": "public"}, {"name": "_get_client", "parameters": ["region"], "visibility": "public"}, {"name": "describe_voices", "visibility": "public"}, {"name": "synthesize_speech", "parameters": ["text"], "visibility": "public"}, {"name": "maybe_get_language_appropriate_voice_", "parameters": ["language"], "visibility": "public"}, {"name": "get_default_voice_for_engine_", "visibility": "public"}]}], "other_elements": [], "element_counts": {"classes": 70, "other": 0, "total_in_ir": 2850}, "_metadata": {"diagram_type": "class", "source_ir": "data/acc878f9-aeca-493c-bc04-48fb2d22d115/ir_postprocessed.json", "project_name": "acc878f9-aeca-493c-bc04-48fb2d22d115", "source_languages": ["javascript"], "source_files_count": 1060, "source_files_sample": ["data/acc878f9-aeca-493c-bc04-48fb2d22d115/exports.js", "data/acc878f9-aeca-493c-bc04-48fb2d22d115/eslint.config.js", "data/acc878f9-aeca-493c-bc04-48fb2d22d115/tools/gen-release-notes.js", "data/acc878f9-aeca-493c-bc04-48fb2d22d115/tools/check-translations.js", "data/acc878f9-aeca-493c-bc04-48fb2d22d115/tools/run-selfhosted.js", "data/acc878f9-aeca-493c-bc04-48fb2d22d115/tools/doc_helper.js", "data/acc878f9-aeca-493c-bc04-48fb2d22d115/tools/validate-eslint.js", "data/acc878f9-aeca-493c-bc04-48fb2d22d115/tools/auth_gui.js", "data/acc878f9-aeca-493c-bc04-48fb2d22d115/extensions/utilities.js", "data/acc878f9-aeca-493c-bc04-48fb2d22d115/extensions/data.js"]}}