{
  "scope": "span_lifecycle",
  "title": "Span Creation and Lifecycle",
  "diagram_type": "sequence",
  "key_participants": [
    "Caller",
    "DDTrace (ext functions)",
    "SpanStack",
    "SpanData",
    "RootSpanData",
    "Span (OT wrapper)"
  ],
  "interaction_flow": [
    "--- New Trace ---",
    "Caller → DDTrace: start_trace_span(float $startTime = 0): RootSpanData",
    "DDTrace → SpanStack: create new root SpanStack, switch active stack",
    "DDTrace → RootSpanData: instantiate with id, parent=null, stack ref",
    "DDTrace → Caller: return RootSpanData",

    "--- Child Span ---",
    "Caller → DDTrace: start_span(float $startTime = 0): SpanData|false",
    "DDTrace → SpanStack: push new SpanData onto active stack (inherits service/env/version from parent)",
    "DDTrace → SpanData: instantiate with id, parent=active_span, stack ref",
    "DDTrace → Caller: return SpanData",
    "NOTE: if no active span exists, start_span behaves like start_trace_span (creates new root stack)",

    "--- Attach Metadata ---",
    "Caller → SpanData: $span->name = 'operation'",
    "Caller → SpanData: $span->resource = 'resource_name'",
    "Caller → SpanData: $span->service = 'service_name'",
    "Caller → SpanData: $span->type = 'web|db|cache|custom'",
    "Caller → SpanData: $span->meta['key'] = 'value'",
    "Caller → SpanData: $span->metrics['key'] = 1.0",
    "Caller → SpanData: $span->links[] = SpanLink (for distributed trace links)",
    "Caller → SpanData: $span->events[] = SpanEvent (for span events)",

    "--- Via OT Span Wrapper ---",
    "Caller → Span: setTag(key, value) — routes special tags (ERROR, SERVICE_NAME, RESOURCE_NAME, SPAN_TYPE, HTTP_URL, HTTP_STATUS_CODE) to internalSpan fields",
    "Caller → Span: setError(Throwable|bool|null) — sets meta[error.msg/type/stack] and hasError flag",
    "Caller → Span: setMetric(key, float) — writes to internalSpan->metrics[]",

    "--- Query Active Span ---",
    "Caller → DDTrace: active_span(): SpanData|null",
    "DDTrace → SpanStack: return SpanStack->active",

    "--- Close Span (normal) ---",
    "Caller → DDTrace: close_span(float $finishTime = 0): false|null",
    "DDTrace → SpanStack: pop top user-span, record finish time, compute duration",
    "DDTrace → SpanData: invoke onClose[] handlers in reverse order",

    "--- Close Span via OT Wrapper ---",
    "Caller → Span: finish(finishTime = null)",
    "Span → DDTrace: active_span() — check if this span is on top",
    "alt span is on top",
    "  Span → DDTrace: close_span(finishTime ?: 0)",
    "alt span NOT on top (out-of-order finish)",
    "  Span → DDTrace: close_spans_until(SpanData $this->internalSpan): false|int",
    "  DDTrace → SpanStack: close all spans above target span (returns count closed)",
    "  Span → DDTrace: close_span(finishTime ?: 0)",

    "--- Update Duration Post-Close ---",
    "Caller → DDTrace: update_span_duration(SpanData $span, float $finishTime = 0): false|null",
    "NOTE: only effective if span not yet flushed; may not work with auto_flush_enabled on root spans",

    "--- Stack Management ---",
    "Caller → DDTrace: switch_stack(SpanData|SpanStack|null): null|false|SpanStack — switch active span context",
    "Caller → DDTrace: root_span(): RootSpanData|null — get root span of active stack"
  ],
  "key_relationships": [
    "RootSpanData extends SpanData (adds: origin, samplingPriority, propagatedTags, parentId, gitMetadata, inferredSpan)",
    "InferredSpanData extends SpanData",
    "SpanData has_readonly parent: SpanData|null",
    "SpanData has_readonly stack: SpanStack",
    "SpanData has onClose: Closure[] — invoked on close, not on drop",
    "SpanStack has active: SpanData|null",
    "SpanStack has parent: SpanStack|null (nested stacks)",
    "Span (OT) wraps SpanData $internalSpan + SpanContext $context",
    "Span::isFinished() checks duration !== 0",
    "DDTrace ext functions operate on thread-local SpanStack"
  ],
  "spandata_key_fields": {
    "identity": ["id (readonly, unique)", "hexId(): string"],
    "naming": ["name: string|null", "resource: string|null", "type: string|null"],
    "routing": ["service: string|null", "env: string", "version: string"],
    "metadata": ["meta: string[]", "metrics: float[]", "meta_struct: array (msgpack-encoded)"],
    "relations": ["parent: SpanData|null (readonly)", "stack: SpanStack (readonly)", "links: SpanLink[]"],
    "events": ["events: SpanEvent[]", "exception: Throwable|null"],
    "timing": ["getStartTime(): int (nanoseconds)", "getDuration(): int (nanoseconds)"],
    "lifecycle": ["onClose: Closure[] (handlers on close)", "baggage: array"]
  },
  "close_spans_until_semantics": "Closes all spans on the active stack above (and not including) the given parent span. Returns false if span is not found, or the count of spans closed. Used for out-of-order finishing.",
  "important_notes": [
    "Times are in seconds (float) for API input, stored/returned in nanoseconds internally",
    "start_span with no active span === start_trace_span (distributed tracing headers applied)",
    "Span::finish() logs a warning if close_spans_until closes multiple spans at once",
    "update_span_duration is unreliable on root spans with auto_flush_enabled",
    "onClose handlers called in reverse order; cleared on close or drop",
    "try_drop_span(SpanData) drops span without metrics, fails if has non-dropped children or distributed links"
  ],
  "source_files_analyzed": [
    "ext/ddtrace.stub.php",
    "src/DDTrace/Span.php"
  ]
}
